mcalc/__init__.py
mcalc/calc.py
mcalc-0.1.8.dist-info/LICENSE
mcalc-0.1.8.dist-info/WHEEL
mcalc-0.1.8.dist-info/METADATA
mcalc-0.1.8.dist-info/RECORD
