Metadata-Version: 2.1
Name: mcalc
Version: 0.1.8
Summary: A simple calculator 
Home-page: https://github.com/Heraldika/calculator
Author: matas tiskus
Author-email: tiskusm@gmail.com
Requires-Python: >=3.6
Classifier: License :: OSI Approved :: MIT License
Requires-Dist: tox ; extra == "test"
Requires-Dist: pytest ; extra == "test"
Requires-Dist: coverage ; extra == "test"
Requires-Dist: flake8 ; extra == "test"
Requires-Dist: mypy ; extra == "test"
Requires-Dist: hypothesis ; extra == "test"
Requires-Dist: black ; extra == "test"
Provides-Extra: test
